himut/__init__.py
himut/__main__.py
himut/bamlib.py
himut/caller.py
himut/cslib.py
himut/gtlib.py
himut/haplib.py
himut/mutlib.py
himut/normcounts.py
himut/parse_args.py
himut/phaselib.py
himut/py.typed
himut/reflib.py
himut/somlib.py
himut/util.py
himut/vcflib.py
himut-1.0.4.dist-info/LICENSE.rst
himut-1.0.4.dist-info/METADATA
himut-1.0.4.dist-info/WHEEL
himut-1.0.4.dist-info/entry_points.txt
himut-1.0.4.dist-info/RECORD
