Metadata-Version: 2.1
Name: himut
Version: 1.0.4
Summary: himut: single molecule somatic single-base substitution detection using PacBio CCS reads
Home-page: https://github.com/sjin09/himut
License: MIT
Author: Sangjin Lee
Author-email: sl17@sanger.ac.uk
Requires-Python: >=3.8,<3.10
Classifier: License :: OSI Approved :: MIT License
Classifier: Programming Language :: Python :: 3
Classifier: Programming Language :: Python :: 3.8
Classifier: Programming Language :: Python :: 3.9
Classifier: Programming Language :: Python :: 3.6
Classifier: Programming Language :: Python :: 3.7
Requires-Dist: argparse (>=1.4.0,<2.0.0)
Requires-Dist: biopython (>=1.78,<2.0)
Requires-Dist: cyvcf2 (>=0.30.18,<0.31.0)
Requires-Dist: natsort (>=8.0.0,<9.0.0)
Requires-Dist: numpy (>=1.20.2,<2.0.0)
Requires-Dist: plotnine (>=0.9.0,<0.10.0)
Requires-Dist: psutil (>=5.8.0,<6.0.0)
Requires-Dist: pyfastx (>=0.8.4,<0.9.0)
Requires-Dist: pyproject-toml (>=0.0.10,<0.0.11)
Requires-Dist: pysam (>=0.18.0,<0.19.0)
Requires-Dist: pytabix (>=0.1,<0.2)
Project-URL: Changelog, https://github.com/sjin09/himut/releases
Project-URL: Repository, https://github.com/sjin09/himut
